{
  "OriginalGameJamData": [
    {
      "m_GjamID": 1,
      "m_Fix": true,
      "m_GjamName": "액션쾌감",
      "m_GjamHost": "대난투 승리자",
      "m_GjamHostIcon": 136,
      "m_GjamDetailInfo": "호쾌한 액션! 짜릿한 쾌감",
      "m_EntryFee": 30000,
      "m_StudentHealth": 10,
      "m_StudentPassion": 5,
      "m_GjamMainGenre": "액션",
      "m_GjamSubGenre": "RPG",
      "m_GjamConcept": "대난투",
      "m_GjamYear": 0,
      "m_GjamMonth": 4,
      "m_GjamWeek": 2,
      "m_GjamTime": 0,
      "m_GjamAI_ID": 300,
      "m_GjamNeedStatGM": {
        "통찰": 0,
        "집중": 0,
        "감각": 5,
        "기술": 4,
        "재치": 0
      },
      "m_GjamNeedStatArt": {
        "통찰": 0,
        "집중": 0,
        "감각": 8,
        "기술": 0,
        "재치": 0
      },
      "m_GjamNeedStatProgramming": {
        "통찰": 6,
        "집중": 6,
        "감각": 0,
        "기술": 0,
        "재치": 0
      },
      "ParticipationReward": 100000
    },
    {
      "m_GjamID": 2,
      "m_Fix": true,
      "m_GjamName": "용사님들을 위한",
      "m_GjamHost": "Rexon",
      "m_GjamHostIcon": 1,
      "m_GjamDetailInfo": "세상을 구할 용사님들을 구합니다",
      "m_EntryFee": 40000,
      "m_StudentHealth": 5,
      "m_StudentPassion": 7,
      "m_GjamMainGenre": "RPG",
      "m_GjamSubGenre": "슈팅",
      "m_GjamConcept": "슈퍼히어로",
      "m_GjamYear": 0,
      "m_GjamMonth": 4,
      "m_GjamWeek": 3,
      "m_GjamTime": 0,
      "m_GjamAI_ID": 300,
      "m_GjamNeedStatGM": {
        "통찰": 0,
        "집중": 10,
        "감각": 0,
        "기술": 8,
        "재치": 0
      },
      "m_GjamNeedStatArt": {
        "통찰": 0,
        "집중": 10,
        "감각": 0,
        "기술": 0,
        "재치": 12
      },
      "m_GjamNeedStatProgramming": {
        "통찰": 0,
        "집중": 0,
        "감각": 0,
        "기술": 12,
        "재치": 0
      },
      "ParticipationReward": 0
    },
    {
      "m_GjamID": 3,
      "m_Fix": true,
      "m_GjamName": "던전 탐험",
      "m_GjamHost": "고대레거시",
      "m_GjamHostIcon": 101,
      "m_GjamDetailInfo": "같이 고대 던전 토벌해요!",
      "m_EntryFee": 45000,
      "m_StudentHealth": 8,
      "m_StudentPassion": 8,
      "m_GjamMainGenre": "퍼즐",
      "m_GjamSubGenre": "어드벤쳐",
      "m_GjamConcept": "고대유적",
      "m_GjamYear": 0,
      "m_GjamMonth": 4,
      "m_GjamWeek": 4,
      "m_GjamTime": 0,
      "m_GjamAI_ID": 300,
      "m_GjamNeedStatGM": {
        "통찰": 0,
        "집중": 0,
        "감각": 6,
        "기술": 0,
        "재치": 12
      },
      "m_GjamNeedStatArt": {
        "통찰": 11,
        "집중": 0,
        "감각": 0,
        "기술": 12,
        "재치": 0
      },
      "m_GjamNeedStatProgramming": {
        "통찰": 0,
        "집중": 0,
        "감각": 6,
        "기술": 0,
        "재치": 15
      },
      "ParticipationReward": 0
    },
    {
      "m_GjamID": 4,
      "m_Fix": true,
      "m_GjamName": "드래곤키우기",
      "m_GjamHost": "최고의 양육자",
      "m_GjamHostIcon": 135,
      "m_GjamDetailInfo": "신개념 드래곤 포획하기, 키우기, 양육하기",
      "m_EntryFee": 40000,
      "m_StudentHealth": 12,
      "m_StudentPassion": 8,
      "m_GjamMainGenre": "시뮬레이션",
      "m_GjamSubGenre": "리듬",
      "m_GjamConcept": "드래곤",
      "m_GjamYear": 0,
      "m_GjamMonth": 5,
      "m_GjamWeek": 1,
      "m_GjamTime": 0,
      "m_GjamAI_ID": 300,
      "m_GjamNeedStatGM": {
        "통찰": 12,
        "집중": 0,
        "감각": 15,
        "기술": 0,
        "재치": 0
      },
      "m_GjamNeedStatArt": {
        "통찰": 0,
        "집중": 0,
        "감각": 16,
        "기술": 0,
        "재치": 10
      },
      "m_GjamNeedStatProgramming": {
        "통찰": 0,
        "집중": 25,
        "감각": 0,
        "기술": 0,
        "재치": 0
      },
      "ParticipationReward": 0
    },
    {
      "m_GjamID": 5,
      "m_Fix": true,
      "m_GjamName": "서바이벌 사파리 ",
      "m_GjamHost": "탕탕웨스트",
      "m_GjamHostIcon": 102,
      "m_GjamDetailInfo": "내 게임으로 에임 실력 확인!",
      "m_EntryFee": 35000,
      "m_StudentHealth": 11,
      "m_StudentPassion": 7,
      "m_GjamMainGenre": "RPG",
      "m_GjamSubGenre": "리듬",
      "m_GjamConcept": "서부총잡이",
      "m_GjamYear": 0,
      "m_GjamMonth": 5,
      "m_GjamWeek": 3,
      "m_GjamTime": 0,
      "m_GjamAI_ID": 300,
      "m_GjamNeedStatGM": {
        "통찰": 0,
        "집중": 17,
        "감각": 0,
        "기술": 13,
        "재치": 0
      },
      "m_GjamNeedStatArt": {
        "통찰": 15,
        "집중": 0,
        "감각": 0,
        "기술": 15,
        "재치": 0
      },
      "m_GjamNeedStatProgramming": {
        "통찰": 17,
        "집중": 0,
        "감각": 0,
        "기술": 8,
        "재치": 0
      },
      "ParticipationReward": 0
    },
    {
      "m_GjamID": 6,
      "m_Fix": true,
      "m_GjamName": "우주 전쟁 ",
      "m_GjamHost": "문어다리",
      "m_GjamHostIcon": 103,
      "m_GjamDetailInfo": "외계인들까지 사로잡을 게임 만들기",
      "m_EntryFee": 30000,
      "m_StudentHealth": 12,
      "m_StudentPassion": 5,
      "m_GjamMainGenre": "슈팅",
      "m_GjamSubGenre": "스포츠",
      "m_GjamConcept": "외계인",
      "m_GjamYear": 0,
      "m_GjamMonth": 5,
      "m_GjamWeek": 4,
      "m_GjamTime": 0,
      "m_GjamAI_ID": 300,
      "m_GjamNeedStatGM": {
        "통찰": 0,
        "집중": 0,
        "감각": 0,
        "기술": 10,
        "재치": 20
      },
      "m_GjamNeedStatArt": {
        "통찰": 6,
        "집중": 24,
        "감각": 0,
        "기술": 0,
        "재치": 0
      },
      "m_GjamNeedStatProgramming": {
        "통찰": 0,
        "집중": 0,
        "감각": 15,
        "기술": 0,
        "재치": 15
      },
      "ParticipationReward": 0
    },
    {
      "m_GjamID": 7,
      "m_Fix": true,
      "m_GjamName": "쉿, 비밀이야",
      "m_GjamHost": "코르그으숲",
      "m_GjamHostIcon": 137,
      "m_GjamDetailInfo": "비밀의 숲, 비밀의 게임",
      "m_EntryFee": 30000,
      "m_StudentHealth": 8,
      "m_StudentPassion": 5,
      "m_GjamMainGenre": "어드벤쳐",
      "m_GjamSubGenre": "퍼즐",
      "m_GjamConcept": "비밀의 숲",
      "m_GjamYear": 0,
      "m_GjamMonth": 6,
      "m_GjamWeek": 1,
      "m_GjamTime": 0,
      "m_GjamAI_ID": 300,
      "m_GjamNeedStatGM": {
        "통찰": 22,
        "집중": 20,
        "감각": 0,
        "기술": 0,
        "재치": 0
      },
      "m_GjamNeedStatArt": {
        "통찰": 0,
        "집중": 0,
        "감각": 0,
        "기술": 25,
        "재치": 15
      },
      "m_GjamNeedStatProgramming": {
        "통찰": 36,
        "집중": 0,
        "감각": 0,
        "기술": 0,
        "재치": 0
      },
      "ParticipationReward": 0
    },
    {
      "m_GjamID": 8,
      "m_Fix": true,
      "m_GjamName": "뉴트로 픽셀",
      "m_GjamHost": "사운드바운스",
      "m_GjamHostIcon": 134,
      "m_GjamDetailInfo": "흥겨운 뉴트로 노인코래방",
      "m_EntryFee": 30000,
      "m_StudentHealth": 8,
      "m_StudentPassion": 9,
      "m_GjamMainGenre": "리듬",
      "m_GjamSubGenre": "슈팅",
      "m_GjamConcept": "노래방",
      "m_GjamYear": 0,
      "m_GjamMonth": 6,
      "m_GjamWeek": 2,
      "m_GjamTime": 0,
      "m_GjamAI_ID": 300,
      "m_GjamNeedStatGM": {
        "통찰": 0,
        "집중": 0,
        "감각": 23,
        "기술": 16,
        "재치": 0
      },
      "m_GjamNeedStatArt": {
        "통찰": 10,
        "집중": 0,
        "감각": 30,
        "기술": 0,
        "재치": 0
      },
      "m_GjamNeedStatProgramming": {
        "통찰": 0,
        "집중": 23,
        "감각": 19,
        "기술": 0,
        "재치": 0
      },
      "ParticipationReward": 0
    },
    {
      "m_GjamID": 9,
      "m_Fix": true,
      "m_GjamName": "두 개의 심장",
      "m_GjamHost": "싸커볼",
      "m_GjamHostIcon": 142,
      "m_GjamDetailInfo": "지치지 않는 두 개의 심장으로 달리기",
      "m_EntryFee": 30000,
      "m_StudentHealth": 8,
      "m_StudentPassion": 11,
      "m_GjamMainGenre": "스포츠",
      "m_GjamSubGenre": "시뮬레이션",
      "m_GjamConcept": "축구",
      "m_GjamYear": 0,
      "m_GjamMonth": 6,
      "m_GjamWeek": 4,
      "m_GjamTime": 0,
      "m_GjamAI_ID": 300,
      "m_GjamNeedStatGM": {
        "통찰": 0,
        "집중": 0,
        "감각": 11,
        "기술": 0,
        "재치": 27
      },
      "m_GjamNeedStatArt": {
        "통찰": 0,
        "집중": 27,
        "감각": 12,
        "기술": 0,
        "재치": 0
      },
      "m_GjamNeedStatProgramming": {
        "통찰": 0,
        "집중": 0,
        "감각": 0,
        "기술": 17,
        "재치": 20
      },
      "ParticipationReward": 0
    },
    {
      "m_GjamID": 10,
      "m_Fix": true,
      "m_GjamName": "엘리멘탈 원정대",
      "m_GjamHost": "스팀다리미",
      "m_GjamHostIcon": 119,
      "m_GjamDetailInfo": "스팀펑크 만들 좀비 같은 개발자 원합니다",
      "m_EntryFee": 40000,
      "m_StudentHealth": 12,
      "m_StudentPassion": 5,
      "m_GjamMainGenre": "RPG",
      "m_GjamSubGenre": "어드벤쳐",
      "m_GjamConcept": "스팀펑크",
      "m_GjamYear": 0,
      "m_GjamMonth": 7,
      "m_GjamWeek": 1,
      "m_GjamTime": 0,
      "m_GjamAI_ID": 300,
      "m_GjamNeedStatGM": {
        "통찰": 0,
        "집중": 0,
        "감각": 0,
        "기술": 25,
        "재치": 25
      },
      "m_GjamNeedStatArt": {
        "통찰": 26,
        "집중": 0,
        "감각": 0,
        "기술": 0,
        "재치": 28
      },
      "m_GjamNeedStatProgramming": {
        "통찰": 0,
        "집중": 0,
        "감각": 42,
        "기술": 0,
        "재치": 0
      },
      "ParticipationReward": 0
    },
    {
      "m_GjamID": 11,
      "m_Fix": true,
      "m_GjamName": "몬스터 매쉬 ",
      "m_GjamHost": "판타지월드",
      "m_GjamHostIcon": 139,
      "m_GjamDetailInfo": "판타지 월드에서 몬스터를 때려잡고 키워서…! 냠냠쩝쩝",
      "m_EntryFee": 45000,
      "m_StudentHealth": 10,
      "m_StudentPassion": 10,
      "m_GjamMainGenre": "액션",
      "m_GjamSubGenre": "시뮬레이션",
      "m_GjamConcept": "판타지",
      "m_GjamYear": 0,
      "m_GjamMonth": 7,
      "m_GjamWeek": 3,
      "m_GjamTime": 0,
      "m_GjamAI_ID": 300,
      "m_GjamNeedStatGM": {
        "통찰": 25,
        "집중": 0,
        "감각": 38,
        "기술": 0,
        "재치": 0
      },
      "m_GjamNeedStatArt": {
        "통찰": 0,
        "집중": 0,
        "감각": 36,
        "기술": 21,
        "재치": 0
      },
      "m_GjamNeedStatProgramming": {
        "통찰": 23,
        "집중": 0,
        "감각": 0,
        "기술": 26,
        "재치": 0
      },
      "ParticipationReward": 0
    },
    {
      "m_GjamID": 12,
      "m_Fix": true,
      "m_GjamName": "리버레코 던전 ",
      "m_GjamHost": "모래시계",
      "m_GjamHostIcon": 106,
      "m_GjamDetailInfo": "현실 갓생을 살기 위하여",
      "m_EntryFee": 35000,
      "m_StudentHealth": 9,
      "m_StudentPassion": 11,
      "m_GjamMainGenre": "퍼즐",
      "m_GjamSubGenre": "슈팅",
      "m_GjamConcept": "시간여행",
      "m_GjamYear": 0,
      "m_GjamMonth": 7,
      "m_GjamWeek": 4,
      "m_GjamTime": 0,
      "m_GjamAI_ID": 300,
      "m_GjamNeedStatGM": {
        "통찰": 0,
        "집중": 46,
        "감각": 0,
        "기술": 0,
        "재치": 0
      },
      "m_GjamNeedStatArt": {
        "통찰": 48,
        "집중": 0,
        "감각": 0,
        "기술": 0,
        "재치": 0
      },
      "m_GjamNeedStatProgramming": {
        "통찰": 0,
        "집중": 20,
        "감각": 0,
        "기술": 0,
        "재치": 28
      },
      "ParticipationReward": 0
    },
    {
      "m_GjamID": 13,
      "m_Fix": true,
      "m_GjamName": "꿈꾸는 개발자",
      "m_GjamHost": "드림캐쳐",
      "m_GjamHostIcon": 140,
      "m_GjamDetailInfo": "꿈은 인생의 사탕입니다",
      "m_EntryFee": 40000,
      "m_StudentHealth": 10,
      "m_StudentPassion": 8,
      "m_GjamMainGenre": "어드벤쳐",
      "m_GjamSubGenre": "슈팅",
      "m_GjamConcept": "꿈",
      "m_GjamYear": 0,
      "m_GjamMonth": 8,
      "m_GjamWeek": 2,
      "m_GjamTime": 0,
      "m_GjamAI_ID": 300,
      "m_GjamNeedStatGM": {
        "통찰": 55,
        "집중": 0,
        "감각": 0,
        "기술": 0,
        "재치": 0
      },
      "m_GjamNeedStatArt": {
        "통찰": 0,
        "집중": 37,
        "감각": 0,
        "기술": 23,
        "재치": 0
      },
      "m_GjamNeedStatProgramming": {
        "통찰": 0,
        "집중": 54,
        "감각": 0,
        "기술": 0,
        "재치": 0
      },
      "ParticipationReward": 0
    },
    {
      "m_GjamID": 14,
      "m_Fix": true,
      "m_GjamName": "슈퍼스매쉬",
      "m_GjamHost": "강백호",
      "m_GjamHostIcon": 109,
      "m_GjamDetailInfo": "왼손은 거들뿐.",
      "m_EntryFee": 45000,
      "m_StudentHealth": 5,
      "m_StudentPassion": 10,
      "m_GjamMainGenre": "스포츠",
      "m_GjamSubGenre": "리듬",
      "m_GjamConcept": "농구",
      "m_GjamYear": 0,
      "m_GjamMonth": 8,
      "m_GjamWeek": 3,
      "m_GjamTime": 0,
      "m_GjamAI_ID": 300,
      "m_GjamNeedStatGM": {
        "통찰": 0,
        "집중": 0,
        "감각": 0,
        "기술": 36,
        "재치": 30
      },
      "m_GjamNeedStatArt": {
        "통찰": 0,
        "집중": 0,
        "감각": 15,
        "기술": 0,
        "재치": 45
      },
      "m_GjamNeedStatProgramming": {
        "통찰": 30,
        "집중": 0,
        "감각": 30,
        "기술": 0,
        "재치": 0
      },
      "ParticipationReward": 0
    },
    {
      "m_GjamID": 15,
      "m_Fix": true,
      "m_GjamName": "아이돌슈팅",
      "m_GjamHost": "스타키우기",
      "m_GjamHostIcon": 122,
      "m_GjamDetailInfo": "스타개발자가 되기위한 스타 키우기",
      "m_EntryFee": 35000,
      "m_StudentHealth": 8,
      "m_StudentPassion": 5,
      "m_GjamMainGenre": "슈팅",
      "m_GjamSubGenre": "스포츠",
      "m_GjamConcept": "아이돌",
      "m_GjamYear": 0,
      "m_GjamMonth": 8,
      "m_GjamWeek": 4,
      "m_GjamTime": 0,
      "m_GjamAI_ID": 300,
      "m_GjamNeedStatGM": {
        "통찰": 0,
        "집중": 20,
        "감각": 42,
        "기술": 0,
        "재치": 0
      },
      "m_GjamNeedStatArt": {
        "통찰": 0,
        "집중": 18,
        "감각": 0,
        "기술": 42,
        "재치": 0
      },
      "m_GjamNeedStatProgramming": {
        "통찰": 0,
        "집중": 0,
        "감각": 0,
        "기술": 29,
        "재치": 25
      },
      "ParticipationReward": 0
    },
    {
      "m_GjamID": 16,
      "m_Fix": true,
      "m_GjamName": "하얀띠부터 품띠까지",
      "m_GjamHost": "스포츠스",
      "m_GjamHostIcon": 138,
      "m_GjamDetailInfo": "하나의 발차기를 만 번 연습합시다",
      "m_EntryFee": 30000,
      "m_StudentHealth": 11,
      "m_StudentPassion": 7,
      "m_GjamMainGenre": "스포츠",
      "m_GjamSubGenre": "액션",
      "m_GjamConcept": "태권도",
      "m_GjamYear": 0,
      "m_GjamMonth": 9,
      "m_GjamWeek": 1,
      "m_GjamTime": 0,
      "m_GjamAI_ID": 300,
      "m_GjamNeedStatGM": {
        "통찰": 0,
        "집중": 64,
        "감각": 0,
        "기술": 0,
        "재치": 0
      },
      "m_GjamNeedStatArt": {
        "통찰": 0,
        "집중": 0,
        "감각": 45,
        "기술": 0,
        "재치": 21
      },
      "m_GjamNeedStatProgramming": {
        "통찰": 45,
        "집중": 24,
        "감각": 0,
        "기술": 0,
        "재치": 0
      },
      "ParticipationReward": 0
    },
    {
      "m_GjamID": 17,
      "m_Fix": true,
      "m_GjamName": "블루소울",
      "m_GjamHost": "십더그",
      "m_GjamHostIcon": 133,
      "m_GjamDetailInfo": "차원을 초월한 사랑을 해보시렵니까?",
      "m_EntryFee": 30000,
      "m_StudentHealth": 8,
      "m_StudentPassion": 7,
      "m_GjamMainGenre": "시뮬레이션",
      "m_GjamSubGenre": "퍼즐",
      "m_GjamConcept": "미소녀",
      "m_GjamYear": 0,
      "m_GjamMonth": 9,
      "m_GjamWeek": 2,
      "m_GjamTime": 0,
      "m_GjamAI_ID": 300,
      "m_GjamNeedStatGM": {
        "통찰": 0,
        "집중": 0,
        "감각": 25,
        "기술": 0,
        "재치": 45
      },
      "m_GjamNeedStatArt": {
        "통찰": 59,
        "집중": 10,
        "감각": 0,
        "기술": 0,
        "재치": 0
      },
      "m_GjamNeedStatProgramming": {
        "통찰": 0,
        "집중": 0,
        "감각": 35,
        "기술": 30,
        "재치": 0
      },
      "ParticipationReward": 0
    },
    {
      "m_GjamID": 18,
      "m_Fix": true,
      "m_GjamName": "제한시간 5일 탈출",
      "m_GjamHost": "정치와권력",
      "m_GjamHostIcon": 141,
      "m_GjamDetailInfo": "망치는 쥐면 두드리고 싶다",
      "m_EntryFee": 40000,
      "m_StudentHealth": 12,
      "m_StudentPassion": 8,
      "m_GjamMainGenre": "어드벤쳐",
      "m_GjamSubGenre": "RPG",
      "m_GjamConcept": "정치권력",
      "m_GjamYear": 0,
      "m_GjamMonth": 9,
      "m_GjamWeek": 3,
      "m_GjamTime": 0,
      "m_GjamAI_ID": 300,
      "m_GjamNeedStatGM": {
        "통찰": 30,
        "집중": 0,
        "감각": 0,
        "기술": 40,
        "재치": 0
      },
      "m_GjamNeedStatArt": {
        "통찰": 0,
        "집중": 65,
        "감각": 0,
        "기술": 0,
        "재치": 0
      },
      "m_GjamNeedStatProgramming": {
        "통찰": 0,
        "집중": 0,
        "감각": 20,
        "기술": 0,
        "재치": 50
      },
      "ParticipationReward": 0
    },
    {
      "m_GjamID": 19,
      "m_Fix": true,
      "m_GjamName": "미래도시 파쿠르",
      "m_GjamHost": "어디에서나 살아남기",
      "m_GjamHostIcon": 107,
      "m_GjamDetailInfo": "미래 생존을 위한 파쿠르 게임",
      "m_EntryFee": 45000,
      "m_StudentHealth": 12,
      "m_StudentPassion": 7,
      "m_GjamMainGenre": "퍼즐",
      "m_GjamSubGenre": "어드벤쳐",
      "m_GjamConcept": "미래도시",
      "m_GjamYear": 0,
      "m_GjamMonth": 10,
      "m_GjamWeek": 1,
      "m_GjamTime": 0,
      "m_GjamAI_ID": 300,
      "m_GjamNeedStatGM": {
        "통찰": 0,
        "집중": 30,
        "감각": 50,
        "기술": 0,
        "재치": 0
      },
      "m_GjamNeedStatArt": {
        "통찰": 42,
        "집중": 0,
        "감각": 0,
        "기술": 36,
        "재치": 0
      },
      "m_GjamNeedStatProgramming": {
        "통찰": 38,
        "집중": 39,
        "감각": 0,
        "기술": 0,
        "재치": 0
      },
      "ParticipationReward": 0
    },
    {
      "m_GjamID": 20,
      "m_Fix": true,
      "m_GjamName": "유뉘티",
      "m_GjamHost": "스팀다리미",
      "m_GjamHostIcon": 119,
      "m_GjamDetailInfo": "스팀다리미에서 유니티 한 잔",
      "m_EntryFee": 30000,
      "m_StudentHealth": 12,
      "m_StudentPassion": 5,
      "m_GjamMainGenre": "리듬",
      "m_GjamSubGenre": "스포츠",
      "m_GjamConcept": "스팀펑크",
      "m_GjamYear": 0,
      "m_GjamMonth": 10,
      "m_GjamWeek": 3,
      "m_GjamTime": 0,
      "m_GjamAI_ID": 300,
      "m_GjamNeedStatGM": {
        "통찰": 47,
        "집중": 0,
        "감각": 0,
        "기술": 0,
        "재치": 32
      },
      "m_GjamNeedStatArt": {
        "통찰": 0,
        "집중": 15,
        "감각": 0,
        "기술": 0,
        "재치": 67
      },
      "m_GjamNeedStatProgramming": {
        "통찰": 40,
        "집중": 0,
        "감각": 0,
        "기술": 40,
        "재치": 0
      },
      "ParticipationReward": 0
    },
    {
      "m_GjamID": 21,
      "m_Fix": true,
      "m_GjamName": "혹으와트 길잡이",
      "m_GjamHost": "마법사 지팡이",
      "m_GjamHostIcon": 143,
      "m_GjamDetailInfo": "지팡이로 보여주는 파격적 액션스쿨",
      "m_EntryFee": 40000,
      "m_StudentHealth": 5,
      "m_StudentPassion": 7,
      "m_GjamMainGenre": "액션",
      "m_GjamSubGenre": "슈팅",
      "m_GjamConcept": "마법",
      "m_GjamYear": 0,
      "m_GjamMonth": 10,
      "m_GjamWeek": 4,
      "m_GjamTime": 0,
      "m_GjamAI_ID": 300,
      "m_GjamNeedStatGM": {
        "통찰": 0,
        "집중": 0,
        "감각": 0,
        "기술": 52,
        "재치": 24
      },
      "m_GjamNeedStatArt": {
        "통찰": 0,
        "집중": 0,
        "감각": 52,
        "기술": 24,
        "재치": 0
      },
      "m_GjamNeedStatProgramming": {
        "통찰": 0,
        "집중": 0,
        "감각": 55,
        "기술": 0,
        "재치": 23
      },
      "ParticipationReward": 0
    },
    {
      "m_GjamID": 22,
      "m_Fix": true,
      "m_GjamName": "검은손",
      "m_GjamHost": "정치와권력",
      "m_GjamHostIcon": 141,
      "m_GjamDetailInfo": "이의있소!",
      "m_EntryFee": 35000,
      "m_StudentHealth": 10,
      "m_StudentPassion": 10,
      "m_GjamMainGenre": "퍼즐",
      "m_GjamSubGenre": "어드벤쳐",
      "m_GjamConcept": "정치권력",
      "m_GjamYear": 0,
      "m_GjamMonth": 11,
      "m_GjamWeek": 1,
      "m_GjamTime": 0,
      "m_GjamAI_ID": 300,
      "m_GjamNeedStatGM": {
        "통찰": 0,
        "집중": 46,
        "감각": 43,
        "기술": 0,
        "재치": 0
      },
      "m_GjamNeedStatArt": {
        "통찰": 37,
        "집중": 48,
        "감각": 0,
        "기술": 0,
        "재치": 0
      },
      "m_GjamNeedStatProgramming": {
        "통찰": 50,
        "집중": 0,
        "감각": 0,
        "기술": 0,
        "재치": 40
      },
      "ParticipationReward": 0
    },
    {
      "m_GjamID": 23,
      "m_Fix": true,
      "m_GjamName": "꿈이라도 좋아 ",
      "m_GjamHost": "드리밍",
      "m_GjamHostIcon": 129,
      "m_GjamDetailInfo": "GI아카데미에 오신걸 환영합니다",
      "m_EntryFee": 35000,
      "m_StudentHealth": 10,
      "m_StudentPassion": 5,
      "m_GjamMainGenre": "시뮬레이션",
      "m_GjamSubGenre": "슈팅",
      "m_GjamConcept": "꿈",
      "m_GjamYear": 0,
      "m_GjamMonth": 11,
      "m_GjamWeek": 2,
      "m_GjamTime": 0,
      "m_GjamAI_ID": 300,
      "m_GjamNeedStatGM": {
        "통찰": 0,
        "집중": 0,
        "감각": 0,
        "기술": 26,
        "재치": 60
      },
      "m_GjamNeedStatArt": {
        "통찰": 0,
        "집중": 0,
        "감각": 0,
        "기술": 62,
        "재치": 27
      },
      "m_GjamNeedStatProgramming": {
        "통찰": 0,
        "집중": 55,
        "감각": 0,
        "기술": 35,
        "재치": 0
      },
      "ParticipationReward": 0
    },
    {
      "m_GjamID": 24,
      "m_Fix": true,
      "m_GjamName": "메이프릴 마을",
      "m_GjamHost": "Rexon",
      "m_GjamHostIcon": 1,
      "m_GjamDetailInfo": "족쇄와 함께 하는 최후의 결전",
      "m_EntryFee": 30000,
      "m_StudentHealth": 5,
      "m_StudentPassion": 5,
      "m_GjamMainGenre": "RPG",
      "m_GjamSubGenre": "어드벤쳐",
      "m_GjamConcept": "검은 마법사",
      "m_GjamYear": 0,
      "m_GjamMonth": 11,
      "m_GjamWeek": 4,
      "m_GjamTime": 0,
      "m_GjamAI_ID": 300,
      "m_GjamNeedStatGM": {
        "통찰": 57,
        "집중": 0,
        "감각": 35,
        "기술": 0,
        "재치": 0
      },
      "m_GjamNeedStatArt": {
        "통찰": 0,
        "집중": 0,
        "감각": 51,
        "기술": 0,
        "재치": 40
      },
      "m_GjamNeedStatProgramming": {
        "통찰": 0,
        "집중": 0,
        "감각": 24,
        "기술": 0,
        "재치": 60
      },
      "ParticipationReward": 0
    },
    {
      "m_GjamID": 25,
      "m_Fix": true,
      "m_GjamName": "게임온!",
      "m_GjamHost": "코인노래방",
      "m_GjamHostIcon": 144,
      "m_GjamDetailInfo": "두룸두룸 둠칫 둠칫 신나는 게임온!",
      "m_EntryFee": 30000,
      "m_StudentHealth": 9,
      "m_StudentPassion": 5,
      "m_GjamMainGenre": "리듬",
      "m_GjamSubGenre": "슈팅",
      "m_GjamConcept": "노래방",
      "m_GjamYear": 0,
      "m_GjamMonth": 12,
      "m_GjamWeek": 2,
      "m_GjamTime": 0,
      "m_GjamAI_ID": 300,
      "m_GjamNeedStatGM": {
        "통찰": 79,
        "집중": 0,
        "감각": 0,
        "기술": 0,
        "재치": 20
      },
      "m_GjamNeedStatArt": {
        "통찰": 61,
        "집중": 0,
        "감각": 38,
        "기술": 0,
        "재치": 0
      },
      "m_GjamNeedStatProgramming": {
        "통찰": 57,
        "집중": 0,
        "감각": 0,
        "기술": 42,
        "재치": 0
      },
      "ParticipationReward": 0
    },
    {
      "m_GjamID": 26,
      "m_Fix": true,
      "m_GjamName": "미소녀 챌린지 ",
      "m_GjamHost": "십더그",
      "m_GjamHostIcon": 133,
      "m_GjamDetailInfo": "세상에서 가장 먼 장거리 연애를 하는 이들을 원해요",
      "m_EntryFee": 50000,
      "m_StudentHealth": 7,
      "m_StudentPassion": 10,
      "m_GjamMainGenre": "액션",
      "m_GjamSubGenre": "시뮬레이션",
      "m_GjamConcept": "미소녀",
      "m_GjamYear": 0,
      "m_GjamMonth": 12,
      "m_GjamWeek": 3,
      "m_GjamTime": 0,
      "m_GjamAI_ID": 300,
      "m_GjamNeedStatGM": {
        "통찰": 0,
        "집중": 20,
        "감각": 0,
        "기술": 85,
        "재치": 0
      },
      "m_GjamNeedStatArt": {
        "통찰": 0,
        "집중": 43,
        "감각": 0,
        "기술": 56,
        "재치": 0
      },
      "m_GjamNeedStatProgramming": {
        "통찰": 0,
        "집중": 70,
        "감각": 35,
        "기술": 0,
        "재치": 0
      },
      "ParticipationReward": 0
    },
    {
      "m_GjamID": 27,
      "m_Fix": true,
      "m_GjamName": "해킹앤플레이",
      "m_GjamHost": "미래도시",
      "m_GjamHostIcon": 145,
      "m_GjamDetailInfo": "미래 세상 속으로 떠나자!",
      "m_EntryFee": 30000,
      "m_StudentHealth": 10,
      "m_StudentPassion": 8,
      "m_GjamMainGenre": "시뮬레이션",
      "m_GjamSubGenre": "퍼즐",
      "m_GjamConcept": "미래도시",
      "m_GjamYear": 0,
      "m_GjamMonth": 12,
      "m_GjamWeek": 4,
      "m_GjamTime": 0,
      "m_GjamAI_ID": 300,
      "m_GjamNeedStatGM": {
        "통찰": 0,
        "집중": 0,
        "감각": 62,
        "기술": 0,
        "재치": 28
      },
      "m_GjamNeedStatArt": {
        "통찰": 0,
        "집중": 89,
        "감각": 0,
        "기술": 0,
        "재치": 10
      },
      "m_GjamNeedStatProgramming": {
        "통찰": 0,
        "집중": 0,
        "감각": 0,
        "기술": 0,
        "재치": 87
      },
      "ParticipationReward": 0
    },
    {
      "m_GjamID": 28,
      "m_Fix": true,
      "m_GjamName": "코딩챌린지",
      "m_GjamHost": "탕탕웨스트",
      "m_GjamHostIcon": 102,
      "m_GjamDetailInfo": "서부 개척시대 카우보이의 낭만",
      "m_EntryFee": 45000,
      "m_StudentHealth": 8,
      "m_StudentPassion": 12,
      "m_GjamMainGenre": "슈팅",
      "m_GjamSubGenre": "RPG",
      "m_GjamConcept": "서부총잡이",
      "m_GjamYear": 0,
      "m_GjamMonth": 1,
      "m_GjamWeek": 1,
      "m_GjamTime": 0,
      "m_GjamAI_ID": 300,
      "m_GjamNeedStatGM": {
        "통찰": 24,
        "집중": 83,
        "감각": 0,
        "기술": 0,
        "재치": 0
      },
      "m_GjamNeedStatArt": {
        "통찰": 0,
        "집중": 39,
        "감각": 66,
        "기술": 0,
        "재치": 0
      },
      "m_GjamNeedStatProgramming": {
        "통찰": 65,
        "집중": 40,
        "감각": 0,
        "기술": 0,
        "재치": 0
      },
      "ParticipationReward": 0
    },
    {
      "m_GjamID": 29,
      "m_Fix": true,
      "m_GjamName": "머코코뉴비판타지",
      "m_GjamHost": "MISOGATE",
      "m_GjamHostIcon": 8,
      "m_GjamDetailInfo": "템포 따라올 수 있는 분만 모집합니다",
      "m_EntryFee": 35000,
      "m_StudentHealth": 11,
      "m_StudentPassion": 5,
      "m_GjamMainGenre": "RPG",
      "m_GjamSubGenre": "액션",
      "m_GjamConcept": "판타지",
      "m_GjamYear": 0,
      "m_GjamMonth": 1,
      "m_GjamWeek": 2,
      "m_GjamTime": 0,
      "m_GjamAI_ID": 300,
      "m_GjamNeedStatGM": {
        "통찰": 0,
        "집중": 30,
        "감각": 74,
        "기술": 0,
        "재치": 0
      },
      "m_GjamNeedStatArt": {
        "통찰": 0,
        "집중": 0,
        "감각": 0,
        "기술": 45,
        "재치": 72
      },
      "m_GjamNeedStatProgramming": {
        "통찰": 0,
        "집중": 0,
        "감각": 38,
        "기술": 69,
        "재치": 0
      },
      "ParticipationReward": 0
    },
    {
      "m_GjamID": 30,
      "m_Fix": true,
      "m_GjamName": "하루만 더",
      "m_GjamHost": "모래시계",
      "m_GjamHostIcon": 106,
      "m_GjamDetailInfo": "십분 만, 한 시간 만, 하루만 더! ",
      "m_EntryFee": 35000,
      "m_StudentHealth": 10,
      "m_StudentPassion": 9,
      "m_GjamMainGenre": "퍼즐",
      "m_GjamSubGenre": "리듬",
      "m_GjamConcept": "시간여행",
      "m_GjamYear": 0,
      "m_GjamMonth": 1,
      "m_GjamWeek": 3,
      "m_GjamTime": 0,
      "m_GjamAI_ID": 300,
      "m_GjamNeedStatGM": {
        "통찰": 0,
        "집중": 0,
        "감각": 0,
        "기술": 65,
        "재치": 55
      },
      "m_GjamNeedStatArt": {
        "통찰": 79,
        "집중": 0,
        "감각": 36,
        "기술": 0,
        "재치": 0
      },
      "m_GjamNeedStatProgramming": {
        "통찰": 0,
        "집중": 86,
        "감각": 0,
        "기술": 0,
        "재치": 27
      },
      "ParticipationReward": 0
    },
    {
      "m_GjamID": 31,
      "m_Fix": true,
      "m_GjamName": "언니얼",
      "m_GjamHost": "2077",
      "m_GjamHostIcon": 120,
      "m_GjamDetailInfo": "언니얼과 함께하는 펑크펑크스팀!",
      "m_EntryFee": 30000,
      "m_StudentHealth": 12,
      "m_StudentPassion": 7,
      "m_GjamMainGenre": "액션",
      "m_GjamSubGenre": "시뮬레이션",
      "m_GjamConcept": "스팀펑크",
      "m_GjamYear": 0,
      "m_GjamMonth": 2,
      "m_GjamWeek": 1,
      "m_GjamTime": 0,
      "m_GjamAI_ID": 300,
      "m_GjamNeedStatGM": {
        "통찰": 96,
        "집중": 0,
        "감각": 20,
        "기술": 0,
        "재치": 0
      },
      "m_GjamNeedStatArt": {
        "통찰": 0,
        "집중": 0,
        "감각": 38,
        "기술": 80,
        "재치": 0
      },
      "m_GjamNeedStatProgramming": {
        "통찰": 20,
        "집중": 0,
        "감각": 97,
        "기술": 0,
        "재치": 0
      },
      "ParticipationReward": 0
    },
    {
      "m_GjamID": 32,
      "m_Fix": true,
      "m_GjamName": "비밀의 문",
      "m_GjamHost": "미로숲",
      "m_GjamHostIcon": 146,
      "m_GjamDetailInfo": "미로숲에서 게임제작 출구 찾기",
      "m_EntryFee": 30000,
      "m_StudentHealth": 10,
      "m_StudentPassion": 8,
      "m_GjamMainGenre": "퍼즐",
      "m_GjamSubGenre": "리듬",
      "m_GjamConcept": "비밀의 숲",
      "m_GjamYear": 0,
      "m_GjamMonth": 2,
      "m_GjamWeek": 3,
      "m_GjamTime": 0,
      "m_GjamAI_ID": 300,
      "m_GjamNeedStatGM": {
        "통찰": 0,
        "집중": 36,
        "감각": 0,
        "기술": 79,
        "재치": 0
      },
      "m_GjamNeedStatArt": {
        "통찰": 0,
        "집중": 60,
        "감각": 0,
        "기술": 0,
        "재치": 60
      },
      "m_GjamNeedStatProgramming": {
        "통찰": 0,
        "집중": 0,
        "감각": 0,
        "기술": 55,
        "재치": 63
      },
      "ParticipationReward": 0
    },
    {
      "m_GjamID": 33,
      "m_Fix": true,
      "m_GjamName": "댄스 댄스 댄브",
      "m_GjamHost": "스타키우기",
      "m_GjamHostIcon": 122,
      "m_GjamDetailInfo": "스타 키우기 대작전",
      "m_EntryFee": 40000,
      "m_StudentHealth": 9,
      "m_StudentPassion": 7,
      "m_GjamMainGenre": "리듬",
      "m_GjamSubGenre": "스포츠",
      "m_GjamConcept": "아이돌",
      "m_GjamYear": 0,
      "m_GjamMonth": 2,
      "m_GjamWeek": 4,
      "m_GjamTime": 0,
      "m_GjamAI_ID": 300,
      "m_GjamNeedStatGM": {
        "통찰": 26,
        "집중": 0,
        "감각": 0,
        "기술": 0,
        "재치": 100
      },
      "m_GjamNeedStatArt": {
        "통찰": 64,
        "집중": 0,
        "감각": 0,
        "기술": 59,
        "재치": 0
      },
      "m_GjamNeedStatProgramming": {
        "통찰": 88,
        "집중": 29,
        "감각": 0,
        "기술": 0,
        "재치": 0
      },
      "ParticipationReward": 0
    },
    {
      "m_GjamID": 100,
      "m_Fix": false,
      "m_GjamName": "게임 퀘스트 연대기 ",
      "m_GjamHost": "MCSOFT",
      "m_GjamHostIcon": 2,
      "m_GjamDetailInfo": "마법사 연대기",
      "m_EntryFee": 45000,
      "m_StudentHealth": 8,
      "m_StudentPassion": 7,
      "m_GjamMainGenre": "슈팅",
      "m_GjamSubGenre": "액션",
      "m_GjamConcept": "마법",
      "m_GjamYear": 0,
      "m_GjamMonth": 4,
      "m_GjamWeek": 0,
      "m_GjamTime": 0,
      "m_GjamAI_ID": 300,
      "m_GjamNeedStatGM": {
        "통찰": 10,
        "집중": 5,
        "감각": 0,
        "기술": 0,
        "재치": 0
      },
      "m_GjamNeedStatArt": {
        "통찰": 0,
        "집중": 0,
        "감각": 0,
        "기술": 0,
        "재치": 10
      },
      "m_GjamNeedStatProgramming": {
        "통찰": 0,
        "집중": 0,
        "감각": 0,
        "기술": 13,
        "재치": 0
      },
      "ParticipationReward": 0
    },
    {
      "m_GjamID": 101,
      "m_Fix": false,
      "m_GjamName": "게임 마라톤",
      "m_GjamHost": "함수",
      "m_GjamHostIcon": 132,
      "m_GjamDetailInfo": "연산과 함께하는 게임 마라톤",
      "m_EntryFee": 30000,
      "m_StudentHealth": 10,
      "m_StudentPassion": 7,
      "m_GjamMainGenre": "어드벤쳐",
      "m_GjamSubGenre": "스포츠",
      "m_GjamConcept": "판타지",
      "m_GjamYear": 0,
      "m_GjamMonth": 4,
      "m_GjamWeek": 0,
      "m_GjamTime": 0,
      "m_GjamAI_ID": 300,
      "m_GjamNeedStatGM": {
        "통찰": 0,
        "집중": 0,
        "감각": 8,
        "기술": 0,
        "재치": 9
      },
      "m_GjamNeedStatArt": {
        "통찰": 15,
        "집중": 0,
        "감각": 0,
        "기술": 0,
        "재치": 0
      },
      "m_GjamNeedStatProgramming": {
        "통찰": 0,
        "집중": 10,
        "감각": 10,
        "기술": 0,
        "재치": 0
      },
      "ParticipationReward": 0
    },
    {
      "m_GjamID": 102,
      "m_Fix": false,
      "m_GjamName": "나이트메어체리",
      "m_GjamHost": "십더그",
      "m_GjamHostIcon": 133,
      "m_GjamDetailInfo": "휴덕은 있어도 탈덕은 없다",
      "m_EntryFee": 45000,
      "m_StudentHealth": 12,
      "m_StudentPassion": 7,
      "m_GjamMainGenre": "시뮬레이션",
      "m_GjamSubGenre": "리듬",
      "m_GjamConcept": "미소녀",
      "m_GjamYear": 0,
      "m_GjamMonth": 4,
      "m_GjamWeek": 0,
      "m_GjamTime": 0,
      "m_GjamAI_ID": 300,
      "m_GjamNeedStatGM": {
        "통찰": 18,
        "집중": 6,
        "감각": 0,
        "기술": 0,
        "재치": 0
      },
      "m_GjamNeedStatArt": {
        "통찰": 5,
        "집중": 10,
        "감각": 0,
        "기술": 0,
        "재치": 0
      },
      "m_GjamNeedStatProgramming": {
        "통찰": 11,
        "집중": 0,
        "감각": 0,
        "기술": 0,
        "재치": 9
      },
      "ParticipationReward": 0
    },
    {
      "m_GjamID": 103,
      "m_Fix": false,
      "m_GjamName": "태권브이",
      "m_GjamHost": "태권소년단",
      "m_GjamHostIcon": 147,
      "m_GjamDetailInfo": "태극마크 달고 게임 만들분 구합니다",
      "m_EntryFee": 30000,
      "m_StudentHealth": 11,
      "m_StudentPassion": 7,
      "m_GjamMainGenre": "스포츠",
      "m_GjamSubGenre": "RPG",
      "m_GjamConcept": "태권도",
      "m_GjamYear": 0,
      "m_GjamMonth": 5,
      "m_GjamWeek": 0,
      "m_GjamTime": 0,
      "m_GjamAI_ID": 300,
      "m_GjamNeedStatGM": {
        "통찰": 0,
        "집중": 0,
        "감각": 19,
        "기술": 7,
        "재치": 0
      },
      "m_GjamNeedStatArt": {
        "통찰": 0,
        "집중": 0,
        "감각": 0,
        "기술": 16,
        "재치": 10
      },
      "m_GjamNeedStatProgramming": {
        "통찰": 0,
        "집중": 0,
        "감각": 7,
        "기술": 20,
        "재치": 0
      },
      "ParticipationReward": 0
    },
    {
      "m_GjamID": 104,
      "m_Fix": false,
      "m_GjamName": "코딩 콜로세움",
      "m_GjamHost": "미래도시",
      "m_GjamHostIcon": 145,
      "m_GjamDetailInfo": "새롭고 혁신적인 창의성을 발휘하라!",
      "m_EntryFee": 30000,
      "m_StudentHealth": 9,
      "m_StudentPassion": 7,
      "m_GjamMainGenre": "퍼즐",
      "m_GjamSubGenre": "어드벤쳐",
      "m_GjamConcept": "미래도시",
      "m_GjamYear": 0,
      "m_GjamMonth": 5,
      "m_GjamWeek": 0,
      "m_GjamTime": 0,
      "m_GjamAI_ID": 300,
      "m_GjamNeedStatGM": {
        "통찰": 20,
        "집중": 6,
        "감각": 0,
        "기술": 0,
        "재치": 0
      },
      "m_GjamNeedStatArt": {
        "통찰": 0,
        "집중": 13,
        "감각": 13,
        "기술": 0,
        "재치": 0
      },
      "m_GjamNeedStatProgramming": {
        "통찰": 0,
        "집중": 8,
        "감각": 0,
        "기술": 0,
        "재치": 18
      },
      "ParticipationReward": 0
    },
    {
      "m_GjamID": 105,
      "m_Fix": false,
      "m_GjamName": "개발자의 묘지",
      "m_GjamHost": "정치와권력",
      "m_GjamHostIcon": 141,
      "m_GjamDetailInfo": "공정한 게임잼을 주도합니다",
      "m_EntryFee": 30000,
      "m_StudentHealth": 5,
      "m_StudentPassion": 9,
      "m_GjamMainGenre": "액션",
      "m_GjamSubGenre": "퍼즐",
      "m_GjamConcept": "정치권력",
      "m_GjamYear": 0,
      "m_GjamMonth": 5,
      "m_GjamWeek": 0,
      "m_GjamTime": 0,
      "m_GjamAI_ID": 300,
      "m_GjamNeedStatGM": {
        "통찰": 0,
        "집중": 0,
        "감각": 5,
        "기술": 0,
        "재치": 21
      },
      "m_GjamNeedStatArt": {
        "통찰": 22,
        "집중": 0,
        "감각": 0,
        "기술": 0,
        "재치": 0
      },
      "m_GjamNeedStatProgramming": {
        "통찰": 15,
        "집중": 15,
        "감각": 0,
        "기술": 0,
        "재치": 0
      },
      "ParticipationReward": 0
    },
    {
      "m_GjamID": 106,
      "m_Fix": false,
      "m_GjamName": "게임 아카데미 ",
      "m_GjamHost": "지아이아카데미",
      "m_GjamHostIcon": 131,
      "m_GjamDetailInfo": "꿈을 이룬 자",
      "m_EntryFee": 25000,
      "m_StudentHealth": 8,
      "m_StudentPassion": 8,
      "m_GjamMainGenre": "RPG",
      "m_GjamSubGenre": "슈팅",
      "m_GjamConcept": "꿈",
      "m_GjamYear": 0,
      "m_GjamMonth": 6,
      "m_GjamWeek": 0,
      "m_GjamTime": 0,
      "m_GjamAI_ID": 300,
      "m_GjamNeedStatGM": {
        "통찰": 0,
        "집중": 0,
        "감각": 0,
        "기술": 13,
        "재치": 25
      },
      "m_GjamNeedStatArt": {
        "통찰": 0,
        "집중": 0,
        "감각": 0,
        "기술": 20,
        "재치": 17
      },
      "m_GjamNeedStatProgramming": {
        "통찰": 20,
        "집중": 0,
        "감각": 20,
        "기술": 0,
        "재치": 0
      },
      "ParticipationReward": 0
    },
    {
      "m_GjamID": 107,
      "m_Fix": false,
      "m_GjamName": "퓨처시티",
      "m_GjamHost": "미래도시",
      "m_GjamHostIcon": 145,
      "m_GjamDetailInfo": "미래의 속삭임",
      "m_EntryFee": 40000,
      "m_StudentHealth": 10,
      "m_StudentPassion": 5,
      "m_GjamMainGenre": "액션",
      "m_GjamSubGenre": "퍼즐",
      "m_GjamConcept": "미래도시",
      "m_GjamYear": 0,
      "m_GjamMonth": 6,
      "m_GjamWeek": 0,
      "m_GjamTime": 0,
      "m_GjamAI_ID": 300,
      "m_GjamNeedStatGM": {
        "통찰": 10,
        "집중": 28,
        "감각": 0,
        "기술": 0,
        "재치": 0
      },
      "m_GjamNeedStatArt": {
        "통찰": 0,
        "집중": 10,
        "감각": 29,
        "기술": 0,
        "재치": 0
      },
      "m_GjamNeedStatProgramming": {
        "통찰": 0,
        "집중": 25,
        "감각": 0,
        "기술": 0,
        "재치": 15
      },
      "ParticipationReward": 0
    },
    {
      "m_GjamID": 108,
      "m_Fix": false,
      "m_GjamName": "슈퍼스매쉬",
      "m_GjamHost": "서태웅",
      "m_GjamHostIcon": 148,
      "m_GjamDetailInfo": "한 발자국도 물러설 생각하지않는 게임 개발",
      "m_EntryFee": 45000,
      "m_StudentHealth": 11,
      "m_StudentPassion": 5,
      "m_GjamMainGenre": "시뮬레이션",
      "m_GjamSubGenre": "RPG",
      "m_GjamConcept": "농구",
      "m_GjamYear": 0,
      "m_GjamMonth": 6,
      "m_GjamWeek": 0,
      "m_GjamTime": 0,
      "m_GjamAI_ID": 300,
      "m_GjamNeedStatGM": {
        "통찰": 0,
        "집중": 0,
        "감각": 35,
        "기술": 0,
        "재치": 0
      },
      "m_GjamNeedStatArt": {
        "통찰": 5,
        "집중": 0,
        "감각": 0,
        "기술": 0,
        "재치": 35
      },
      "m_GjamNeedStatProgramming": {
        "통찰": 0,
        "집중": 0,
        "감각": 0,
        "기술": 35,
        "재치": 0
      },
      "ParticipationReward": 0
    },
    {
      "m_GjamID": 109,
      "m_Fix": false,
      "m_GjamName": "격투의 대가",
      "m_GjamHost": "파이터즈",
      "m_GjamHostIcon": 149,
      "m_GjamDetailInfo": "열정과 땀들의 난투극",
      "m_EntryFee": 30000,
      "m_StudentHealth": 10,
      "m_StudentPassion": 7,
      "m_GjamMainGenre": "RPG",
      "m_GjamSubGenre": "액션",
      "m_GjamConcept": "대난투",
      "m_GjamYear": 0,
      "m_GjamMonth": 7,
      "m_GjamWeek": 0,
      "m_GjamTime": 0,
      "m_GjamAI_ID": 300,
      "m_GjamNeedStatGM": {
        "통찰": 0,
        "집중": 0,
        "감각": 0,
        "기술": 10,
        "재치": 40
      },
      "m_GjamNeedStatArt": {
        "통찰": 31,
        "집중": 19,
        "감각": 0,
        "기술": 0,
        "재치": 0
      },
      "m_GjamNeedStatProgramming": {
        "통찰": 30,
        "집중": 0,
        "감각": 20,
        "기술": 0,
        "재치": 0
      },
      "ParticipationReward": 0
    },
    {
      "m_GjamID": 110,
      "m_Fix": false,
      "m_GjamName": "캐릭캐릭챌린지",
      "m_GjamHost": "십더그",
      "m_GjamHostIcon": 133,
      "m_GjamDetailInfo": "어둠속 심연에서 찬란한 빛을 찾아라",
      "m_EntryFee": 45000,
      "m_StudentHealth": 9,
      "m_StudentPassion": 6,
      "m_GjamMainGenre": "슈팅",
      "m_GjamSubGenre": "스포츠",
      "m_GjamConcept": "미소녀",
      "m_GjamYear": 0,
      "m_GjamMonth": 7,
      "m_GjamWeek": 0,
      "m_GjamTime": 0,
      "m_GjamAI_ID": 300,
      "m_GjamNeedStatGM": {
        "통찰": 25,
        "집중": 25,
        "감각": 0,
        "기술": 0,
        "재치": 0
      },
      "m_GjamNeedStatArt": {
        "통찰": 0,
        "집중": 0,
        "감각": 0,
        "기술": 42,
        "재치": 5
      },
      "m_GjamNeedStatProgramming": {
        "통찰": 0,
        "집중": 0,
        "감각": 42,
        "기술": 0,
        "재치": 0
      },
      "ParticipationReward": 0
    },
    {
      "m_GjamID": 111,
      "m_Fix": false,
      "m_GjamName": "마법 스쿨",
      "m_GjamHost": "마법사들",
      "m_GjamHostIcon": 150,
      "m_GjamDetailInfo": "마법같은 게임 이야기",
      "m_EntryFee": 30000,
      "m_StudentHealth": 10,
      "m_StudentPassion": 6,
      "m_GjamMainGenre": "리듬",
      "m_GjamSubGenre": "시뮬레이션",
      "m_GjamConcept": "마법",
      "m_GjamYear": 0,
      "m_GjamMonth": 7,
      "m_GjamWeek": 0,
      "m_GjamTime": 0,
      "m_GjamAI_ID": 300,
      "m_GjamNeedStatGM": {
        "통찰": 0,
        "집중": 0,
        "감각": 20,
        "기술": 30,
        "재치": 0
      },
      "m_GjamNeedStatArt": {
        "통찰": 0,
        "집중": 47,
        "감각": 0,
        "기술": 0,
        "재치": 0
      },
      "m_GjamNeedStatProgramming": {
        "통찰": 0,
        "집중": 5,
        "감각": 0,
        "기술": 0,
        "재치": 45
      },
      "ParticipationReward": 0
    },
    {
      "m_GjamID": 112,
      "m_Fix": false,
      "m_GjamName": "게임 히어로",
      "m_GjamHost": "슈퍼히어로",
      "m_GjamHostIcon": 151,
      "m_GjamDetailInfo": "게임 업계의 히어로를 모집합니다",
      "m_EntryFee": 35000,
      "m_StudentHealth": 11,
      "m_StudentPassion": 8,
      "m_GjamMainGenre": "액션",
      "m_GjamSubGenre": "퍼즐",
      "m_GjamConcept": "슈퍼히어로",
      "m_GjamYear": 0,
      "m_GjamMonth": 8,
      "m_GjamWeek": 0,
      "m_GjamTime": 0,
      "m_GjamAI_ID": 300,
      "m_GjamNeedStatGM": {
        "통찰": 47,
        "집중": 0,
        "감각": 0,
        "기술": 0,
        "재치": 10
      },
      "m_GjamNeedStatArt": {
        "통찰": 0,
        "집중": 0,
        "감각": 0,
        "기술": 6,
        "재치": 53
      },
      "m_GjamNeedStatProgramming": {
        "통찰": 0,
        "집중": 0,
        "감각": 0,
        "기술": 32,
        "재치": 28
      },
      "ParticipationReward": 0
    },
    {
      "m_GjamID": 113,
      "m_Fix": false,
      "m_GjamName": "태초마을",
      "m_GjamHost": "드래곤 빌리지",
      "m_GjamHostIcon": 152,
      "m_GjamDetailInfo": "드래곤 빌리지의 태초마을 게임잼",
      "m_EntryFee": 30000,
      "m_StudentHealth": 12,
      "m_StudentPassion": 7,
      "m_GjamMainGenre": "RPG",
      "m_GjamSubGenre": "어드벤쳐",
      "m_GjamConcept": "드래곤",
      "m_GjamYear": 0,
      "m_GjamMonth": 8,
      "m_GjamWeek": 0,
      "m_GjamTime": 0,
      "m_GjamAI_ID": 300,
      "m_GjamNeedStatGM": {
        "통찰": 0,
        "집중": 55,
        "감각": 0,
        "기술": 0,
        "재치": 0
      },
      "m_GjamNeedStatArt": {
        "통찰": 0,
        "집중": 0,
        "감각": 58,
        "기술": 0,
        "재치": 0
      },
      "m_GjamNeedStatProgramming": {
        "통찰": 0,
        "집중": 37,
        "감각": 21,
        "기술": 0,
        "재치": 0
      },
      "ParticipationReward": 0
    },
    {
      "m_GjamID": 114,
      "m_Fix": false,
      "m_GjamName": "게임 마라톤",
      "m_GjamHost": "정치와권력",
      "m_GjamHostIcon": 141,
      "m_GjamDetailInfo": "권력자들과 함께하는 게임 마라톤",
      "m_EntryFee": 25000,
      "m_StudentHealth": 12,
      "m_StudentPassion": 5,
      "m_GjamMainGenre": "시뮬레이션",
      "m_GjamSubGenre": "퍼즐",
      "m_GjamConcept": "정치권력",
      "m_GjamYear": 0,
      "m_GjamMonth": 8,
      "m_GjamWeek": 0,
      "m_GjamTime": 0,
      "m_GjamAI_ID": 300,
      "m_GjamNeedStatGM": {
        "통찰": 0,
        "집중": 0,
        "감각": 58,
        "기술": 0,
        "재치": 0
      },
      "m_GjamNeedStatArt": {
        "통찰": 25,
        "집중": 0,
        "감각": 35,
        "기술": 0,
        "재치": 0
      },
      "m_GjamNeedStatProgramming": {
        "통찰": 41,
        "집중": 0,
        "감각": 0,
        "기술": 15,
        "재치": 0
      },
      "ParticipationReward": 0
    },
    {
      "m_GjamID": 115,
      "m_Fix": false,
      "m_GjamName": "문명의 사회",
      "m_GjamHost": "고대유적탐험대",
      "m_GjamHostIcon": 153,
      "m_GjamDetailInfo": "문명사회에서 고대 유적 찾기",
      "m_EntryFee": 40000,
      "m_StudentHealth": 10,
      "m_StudentPassion": 6,
      "m_GjamMainGenre": "슈팅",
      "m_GjamSubGenre": "시뮬레이션",
      "m_GjamConcept": "고대유적",
      "m_GjamYear": 0,
      "m_GjamMonth": 9,
      "m_GjamWeek": 0,
      "m_GjamTime": 0,
      "m_GjamAI_ID": 300,
      "m_GjamNeedStatGM": {
        "통찰": 50,
        "집중": 0,
        "감각": 0,
        "기술": 0,
        "재치": 20
      },
      "m_GjamNeedStatArt": {
        "통찰": 45,
        "집중": 25,
        "감각": 0,
        "기술": 0,
        "재치": 0
      },
      "m_GjamNeedStatProgramming": {
        "통찰": 0,
        "집중": 55,
        "감각": 0,
        "기술": 0,
        "재치": 12
      },
      "ParticipationReward": 0
    },
    {
      "m_GjamID": 116,
      "m_Fix": false,
      "m_GjamName": "노래길잡이",
      "m_GjamHost": "DJ팍",
      "m_GjamHostIcon": 154,
      "m_GjamDetailInfo": "흥을 돋을 게임 개발자 모집합니다",
      "m_EntryFee": 35000,
      "m_StudentHealth": 8,
      "m_StudentPassion": 7,
      "m_GjamMainGenre": "액션",
      "m_GjamSubGenre": "리듬",
      "m_GjamConcept": "노래방",
      "m_GjamYear": 0,
      "m_GjamMonth": 9,
      "m_GjamWeek": 0,
      "m_GjamTime": 0,
      "m_GjamAI_ID": 300,
      "m_GjamNeedStatGM": {
        "통찰": 0,
        "집중": 10,
        "감각": 0,
        "기술": 61,
        "재치": 0
      },
      "m_GjamNeedStatArt": {
        "통찰": 0,
        "집중": 0,
        "감각": 0,
        "기술": 63,
        "재치": 5
      },
      "m_GjamNeedStatProgramming": {
        "통찰": 13,
        "집중": 0,
        "감각": 52,
        "기술": 0,
        "재치": 0
      },
      "ParticipationReward": 0
    },
    {
      "m_GjamID": 117,
      "m_Fix": false,
      "m_GjamName": "축구공은 육각형",
      "m_GjamHost": "휘바휘바",
      "m_GjamHostIcon": 156,
      "m_GjamDetailInfo": "신규 축구 모드 만들기",
      "m_EntryFee": 30000,
      "m_StudentHealth": 11,
      "m_StudentPassion": 9,
      "m_GjamMainGenre": "리듬",
      "m_GjamSubGenre": "스포츠",
      "m_GjamConcept": "축구",
      "m_GjamYear": 0,
      "m_GjamMonth": 9,
      "m_GjamWeek": 0,
      "m_GjamTime": 0,
      "m_GjamAI_ID": 300,
      "m_GjamNeedStatGM": {
        "통찰": 0,
        "집중": 0,
        "감각": 0,
        "기술": 0,
        "재치": 65
      },
      "m_GjamNeedStatArt": {
        "통찰": 0,
        "집중": 0,
        "감각": 0,
        "기술": 12,
        "재치": 57
      },
      "m_GjamNeedStatProgramming": {
        "통찰": 0,
        "집중": 0,
        "감각": 0,
        "기술": 35,
        "재치": 35
      },
      "ParticipationReward": 0
    },
    {
      "m_GjamID": 118,
      "m_Fix": false,
      "m_GjamName": "최고의 총",
      "m_GjamHost": "댄저러스맨",
      "m_GjamHostIcon": 158,
      "m_GjamDetailInfo": "서부 개척시대 카우보이의 낭만",
      "m_EntryFee": 25000,
      "m_StudentHealth": 10,
      "m_StudentPassion": 10,
      "m_GjamMainGenre": "어드벤쳐",
      "m_GjamSubGenre": "슈팅",
      "m_GjamConcept": "서부 총잡이",
      "m_GjamYear": 0,
      "m_GjamMonth": 10,
      "m_GjamWeek": 0,
      "m_GjamTime": 0,
      "m_GjamAI_ID": 300,
      "m_GjamNeedStatGM": {
        "통찰": 75,
        "집중": 0,
        "감각": 0,
        "기술": 0,
        "재치": 0
      },
      "m_GjamNeedStatArt": {
        "통찰": 0,
        "집중": 40,
        "감각": 40,
        "기술": 0,
        "재치": 0
      },
      "m_GjamNeedStatProgramming": {
        "통찰": 0,
        "집중": 40,
        "감각": 40,
        "기술": 0,
        "재치": 0
      },
      "ParticipationReward": 0
    },
    {
      "m_GjamID": 119,
      "m_Fix": false,
      "m_GjamName": "시크릿하우스",
      "m_GjamHost": "미로숲",
      "m_GjamHostIcon": 146,
      "m_GjamDetailInfo": "비밀리에 진행되는 위대한 게임 개발",
      "m_EntryFee": 40000,
      "m_StudentHealth": 11,
      "m_StudentPassion": 5,
      "m_GjamMainGenre": "시뮬레이션",
      "m_GjamSubGenre": "액션",
      "m_GjamConcept": "비밀의 숲",
      "m_GjamYear": 0,
      "m_GjamMonth": 10,
      "m_GjamWeek": 0,
      "m_GjamTime": 0,
      "m_GjamAI_ID": 300,
      "m_GjamNeedStatGM": {
        "통찰": 0,
        "집중": 45,
        "감각": 32,
        "기술": 0,
        "재치": 0
      },
      "m_GjamNeedStatArt": {
        "통찰": 0,
        "집중": 0,
        "감각": 0,
        "기술": 60,
        "재치": 20
      },
      "m_GjamNeedStatProgramming": {
        "통찰": 73,
        "집중": 0,
        "감각": 0,
        "기술": 0,
        "재치": 0
      },
      "ParticipationReward": 0
    },
    {
      "m_GjamID": 120,
      "m_Fix": false,
      "m_GjamName": "타임포스",
      "m_GjamHost": "모래시계",
      "m_GjamHostIcon": 106,
      "m_GjamDetailInfo": "게임 개발에서 가장 중요한 것은, 시간여행",
      "m_EntryFee": 35000,
      "m_StudentHealth": 10,
      "m_StudentPassion": 5,
      "m_GjamMainGenre": "RPG",
      "m_GjamSubGenre": "스포츠",
      "m_GjamConcept": "시간여행",
      "m_GjamYear": 0,
      "m_GjamMonth": 10,
      "m_GjamWeek": 0,
      "m_GjamTime": 0,
      "m_GjamAI_ID": 300,
      "m_GjamNeedStatGM": {
        "통찰": 0,
        "집중": 0,
        "감각": 0,
        "기술": 49,
        "재치": 30
      },
      "m_GjamNeedStatArt": {
        "통찰": 62,
        "집중": 17,
        "감각": 0,
        "기술": 0,
        "재치": 0
      },
      "m_GjamNeedStatProgramming": {
        "통찰": 0,
        "집중": 15,
        "감각": 0,
        "기술": 62,
        "재치": 0
      },
      "ParticipationReward": 0
    },
    {
      "m_GjamID": 121,
      "m_Fix": false,
      "m_GjamName": "게임 구하기",
      "m_GjamHost": "히어로슈퍼",
      "m_GjamHostIcon": 155,
      "m_GjamDetailInfo": "게임 업계를 구할 슈퍼히어로 절찬리 모집",
      "m_EntryFee": 45000,
      "m_StudentHealth": 12,
      "m_StudentPassion": 7,
      "m_GjamMainGenre": "액션",
      "m_GjamSubGenre": "슈팅",
      "m_GjamConcept": "슈퍼히어로",
      "m_GjamYear": 0,
      "m_GjamMonth": 11,
      "m_GjamWeek": 0,
      "m_GjamTime": 0,
      "m_GjamAI_ID": 300,
      "m_GjamNeedStatGM": {
        "통찰": 50,
        "집중": 0,
        "감각": 0,
        "기술": 40,
        "재치": 0
      },
      "m_GjamNeedStatArt": {
        "통찰": 38,
        "집중": 54,
        "감각": 0,
        "기술": 0,
        "재치": 0
      },
      "m_GjamNeedStatProgramming": {
        "통찰": 0,
        "집중": 43,
        "감각": 0,
        "기술": 0,
        "재치": 42
      },
      "ParticipationReward": 0
    },
    {
      "m_GjamID": 122,
      "m_Fix": false,
      "m_GjamName": "뉴비학살자",
      "m_GjamHost": "외계인",
      "m_GjamHostIcon": 159,
      "m_GjamDetailInfo": "뉴비는 가라! 게임잼 고수를 모집합니다",
      "m_EntryFee": 50000,
      "m_StudentHealth": 8,
      "m_StudentPassion": 2,
      "m_GjamMainGenre": "리듬",
      "m_GjamSubGenre": "시뮬레이션",
      "m_GjamConcept": "외계인",
      "m_GjamYear": 0,
      "m_GjamMonth": 11,
      "m_GjamWeek": 0,
      "m_GjamTime": 0,
      "m_GjamAI_ID": 300,
      "m_GjamNeedStatGM": {
        "통찰": 0,
        "집중": 45,
        "감각": 45,
        "기술": 0,
        "재치": 0
      },
      "m_GjamNeedStatArt": {
        "통찰": 0,
        "집중": 0,
        "감각": 42,
        "기술": 0,
        "재치": 50
      },
      "m_GjamNeedStatProgramming": {
        "통찰": 20,
        "집중": 0,
        "감각": 0,
        "기술": 0,
        "재치": 63
      },
      "ParticipationReward": 0
    },
    {
      "m_GjamID": 123,
      "m_Fix": false,
      "m_GjamName": "농구코딩슬래시",
      "m_GjamHost": "농구게임협회",
      "m_GjamHostIcon": 157,
      "m_GjamDetailInfo": "통통 튀기는 우리의 게임 개발",
      "m_EntryFee": 40000,
      "m_StudentHealth": 8,
      "m_StudentPassion": 5,
      "m_GjamMainGenre": "스포츠",
      "m_GjamSubGenre": "퍼즐",
      "m_GjamConcept": "농구",
      "m_GjamYear": 0,
      "m_GjamMonth": 11,
      "m_GjamWeek": 0,
      "m_GjamTime": 0,
      "m_GjamAI_ID": 300,
      "m_GjamNeedStatGM": {
        "통찰": 67,
        "집중": 0,
        "감각": 0,
        "기술": 0,
        "재치": 23
      },
      "m_GjamNeedStatArt": {
        "통찰": 0,
        "집중": 0,
        "감각": 22,
        "기술": 77,
        "재치": 0
      },
      "m_GjamNeedStatProgramming": {
        "통찰": 0,
        "집중": 0,
        "감각": 80,
        "기술": 10,
        "재치": 0
      },
      "ParticipationReward": 0
    },
    {
      "m_GjamID": 124,
      "m_Fix": false,
      "m_GjamName": "아이돌마스터",
      "m_GjamHost": "스타키우기",
      "m_GjamHostIcon": 122,
      "m_GjamDetailInfo": "스타 만들기 대작전",
      "m_EntryFee": 45000,
      "m_StudentHealth": 9,
      "m_StudentPassion": 5,
      "m_GjamMainGenre": "RPG",
      "m_GjamSubGenre": "퍼즐",
      "m_GjamConcept": "아이돌",
      "m_GjamYear": 0,
      "m_GjamMonth": 12,
      "m_GjamWeek": 0,
      "m_GjamTime": 0,
      "m_GjamAI_ID": 300,
      "m_GjamNeedStatGM": {
        "통찰": 0,
        "집중": 50,
        "감각": 0,
        "기술": 0,
        "재치": 50
      },
      "m_GjamNeedStatArt": {
        "통찰": 28,
        "집중": 71,
        "감각": 0,
        "기술": 0,
        "재치": 0
      },
      "m_GjamNeedStatProgramming": {
        "통찰": 42,
        "집중": 0,
        "감각": 0,
        "기술": 56,
        "재치": 0
      },
      "ParticipationReward": 0
    },
    {
      "m_GjamID": 125,
      "m_Fix": false,
      "m_GjamName": "히어로 스쿨멘션",
      "m_GjamHost": "슈퍼히어로",
      "m_GjamHostIcon": 151,
      "m_GjamDetailInfo": "너만의 슈퍼 히어로를 만들어 봐",
      "m_EntryFee": 30000,
      "m_StudentHealth": 9,
      "m_StudentPassion": 5,
      "m_GjamMainGenre": "슈팅",
      "m_GjamSubGenre": "액션",
      "m_GjamConcept": "슈퍼히어로",
      "m_GjamYear": 0,
      "m_GjamMonth": 12,
      "m_GjamWeek": 0,
      "m_GjamTime": 0,
      "m_GjamAI_ID": 300,
      "m_GjamNeedStatGM": {
        "통찰": 0,
        "집중": 0,
        "감각": 0,
        "기술": 0,
        "재치": 94
      },
      "m_GjamNeedStatArt": {
        "통찰": 0,
        "집중": 0,
        "감각": 0,
        "기술": 20,
        "재치": 80
      },
      "m_GjamNeedStatProgramming": {
        "통찰": 0,
        "집중": 70,
        "감각": 0,
        "기술": 0,
        "재치": 20
      },
      "ParticipationReward": 0
    },
    {
      "m_GjamID": 126,
      "m_Fix": false,
      "m_GjamName": "잊혀지고싶지 않은",
      "m_GjamHost": "고대유적탐험대",
      "m_GjamHostIcon": 153,
      "m_GjamDetailInfo": "레드 오션 속 잊혀진 새로움 찾기",
      "m_EntryFee": 45000,
      "m_StudentHealth": 10,
      "m_StudentPassion": 7,
      "m_GjamMainGenre": "어드벤쳐",
      "m_GjamSubGenre": "RPG",
      "m_GjamConcept": "고대 유적",
      "m_GjamYear": 0,
      "m_GjamMonth": 12,
      "m_GjamWeek": 0,
      "m_GjamTime": 0,
      "m_GjamAI_ID": 300,
      "m_GjamNeedStatGM": {
        "통찰": 68,
        "집중": 0,
        "감각": 30,
        "기술": 0,
        "재치": 0
      },
      "m_GjamNeedStatArt": {
        "통찰": 0,
        "집중": 82,
        "감각": 12,
        "기술": 0,
        "재치": 0
      },
      "m_GjamNeedStatProgramming": {
        "통찰": 0,
        "집중": 0,
        "감각": 0,
        "기술": 0,
        "재치": 83
      },
      "ParticipationReward": 0
    },
    {
      "m_GjamID": 127,
      "m_Fix": false,
      "m_GjamName": "공굴러가유",
      "m_GjamHost": "싸커볼",
      "m_GjamHostIcon": 142,
      "m_GjamDetailInfo": "굴러가기만 하면 뭐든 되는 게임잼",
      "m_EntryFee": 30000,
      "m_StudentHealth": 11,
      "m_StudentPassion": 7,
      "m_GjamMainGenre": "시뮬레이션",
      "m_GjamSubGenre": "리듬",
      "m_GjamConcept": "축구",
      "m_GjamYear": 0,
      "m_GjamMonth": 1,
      "m_GjamWeek": 0,
      "m_GjamTime": 0,
      "m_GjamAI_ID": 300,
      "m_GjamNeedStatGM": {
        "통찰": 0,
        "집중": 0,
        "감각": 75,
        "기술": 31,
        "재치": 0
      },
      "m_GjamNeedStatArt": {
        "통찰": 83,
        "집중": 0,
        "감각": 0,
        "기술": 22,
        "재치": 0
      },
      "m_GjamNeedStatProgramming": {
        "통찰": 50,
        "집중": 0,
        "감각": 60,
        "기술": 0,
        "재치": 0
      },
      "ParticipationReward": 0
    },
    {
      "m_GjamID": 128,
      "m_Fix": false,
      "m_GjamName": "개발일지",
      "m_GjamHost": "파이터즈",
      "m_GjamHostIcon": 149,
      "m_GjamDetailInfo": "게임 개발 조차 게임인 세상",
      "m_EntryFee": 30000,
      "m_StudentHealth": 11,
      "m_StudentPassion": 5,
      "m_GjamMainGenre": "스포츠",
      "m_GjamSubGenre": "어드벤쳐",
      "m_GjamConcept": "대난투",
      "m_GjamYear": 0,
      "m_GjamMonth": 1,
      "m_GjamWeek": 0,
      "m_GjamTime": 0,
      "m_GjamAI_ID": 300,
      "m_GjamNeedStatGM": {
        "통찰": 0,
        "집중": 0,
        "감각": 0,
        "기술": 82,
        "재치": 0
      },
      "m_GjamNeedStatArt": {
        "통찰": 0,
        "집중": 0,
        "감각": 86,
        "기술": 0,
        "재치": 0
      },
      "m_GjamNeedStatProgramming": {
        "통찰": 0,
        "집중": 30,
        "감각": 0,
        "기술": 73,
        "재치": 0
      },
      "ParticipationReward": 0
    },
    {
      "m_GjamID": 129,
      "m_Fix": false,
      "m_GjamName": "코딩 콜로세움",
      "m_GjamHost": "정치와권력",
      "m_GjamHostIcon": 141,
      "m_GjamDetailInfo": "집탄율의 중요성",
      "m_EntryFee": 30000,
      "m_StudentHealth": 12,
      "m_StudentPassion": 7,
      "m_GjamMainGenre": "슈팅",
      "m_GjamSubGenre": "어드벤쳐",
      "m_GjamConcept": "정치권력",
      "m_GjamYear": 0,
      "m_GjamMonth": 1,
      "m_GjamWeek": 0,
      "m_GjamTime": 0,
      "m_GjamAI_ID": 300,
      "m_GjamNeedStatGM": {
        "통찰": 0,
        "집중": 0,
        "감각": 0,
        "기술": 53,
        "재치": 57
      },
      "m_GjamNeedStatArt": {
        "통찰": 0,
        "집중": 0,
        "감각": 0,
        "기술": 35,
        "재치": 72
      },
      "m_GjamNeedStatProgramming": {
        "통찰": 90,
        "집중": 0,
        "감각": 0,
        "기술": 0,
        "재치": 0
      },
      "ParticipationReward": 0
    },
    {
      "m_GjamID": 130,
      "m_Fix": false,
      "m_GjamName": "용과 함께",
      "m_GjamHost": "드래곤 빌리지",
      "m_GjamHostIcon": 152,
      "m_GjamDetailInfo": "하늘에서 펼쳐지는 용드래곤 액션",
      "m_EntryFee": 25000,
      "m_StudentHealth": 12,
      "m_StudentPassion": 4,
      "m_GjamMainGenre": "RPG",
      "m_GjamSubGenre": "시뮬레이션",
      "m_GjamConcept": "드래곤",
      "m_GjamYear": 0,
      "m_GjamMonth": 2,
      "m_GjamWeek": 0,
      "m_GjamTime": 0,
      "m_GjamAI_ID": 300,
      "m_GjamNeedStatGM": {
        "통찰": 92,
        "집중": 15,
        "감각": 0,
        "기술": 0,
        "재치": 0
      },
      "m_GjamNeedStatArt": {
        "통찰": 0,
        "집중": 60,
        "감각": 60,
        "기술": 0,
        "재치": 0
      },
      "m_GjamNeedStatProgramming": {
        "통찰": 0,
        "집중": 60,
        "감각": 0,
        "기술": 61,
        "재치": 0
      },
      "ParticipationReward": 0
    },
    {
      "m_GjamID": 131,
      "m_Fix": false,
      "m_GjamName": "고인물",
      "m_GjamHost": "외계인",
      "m_GjamHostIcon": 159,
      "m_GjamDetailInfo": "상상을 현실로 만들 수 있는 게임잼",
      "m_EntryFee": 35000,
      "m_StudentHealth": 10,
      "m_StudentPassion": 5,
      "m_GjamMainGenre": "액션",
      "m_GjamSubGenre": "어드벤쳐",
      "m_GjamConcept": "외계인",
      "m_GjamYear": 0,
      "m_GjamMonth": 2,
      "m_GjamWeek": 0,
      "m_GjamTime": 0,
      "m_GjamAI_ID": 300,
      "m_GjamNeedStatGM": {
        "통찰": 0,
        "집중": 0,
        "감각": 60,
        "기술": 60,
        "재치": 0
      },
      "m_GjamNeedStatArt": {
        "통찰": 65,
        "집중": 0,
        "감각": 0,
        "기술": 45,
        "재치": 0
      },
      "m_GjamNeedStatProgramming": {
        "통찰": 58,
        "집중": 0,
        "감각": 0,
        "기술": 0,
        "재치": 58
      },
      "ParticipationReward": 0
    }
  ]
}